digma/instrumentation/test_tools/__init__.py
digma/instrumentation/test_tools/helpers.py
digma/instrumentation/test_tools/otlp_exporter_for_tests.py
digma/instrumentation/test_tools/version.py
digma_instrumentation_testtools-0.9.0.dist-info/METADATA
digma_instrumentation_testtools-0.9.0.dist-info/WHEEL
digma_instrumentation_testtools-0.9.0.dist-info/top_level.txt
digma_instrumentation_testtools-0.9.0.dist-info/RECORD
