Metadata-Version: 2.1
Name: digma-instrumentation-testtools
Version: 0.9.0
Summary: Digma instrumentation for Python testing tools
Home-page: https://github.com/digma-ai/opentelemetry-instrumentation-digma
Author: Roni Dover
Author-email: rdover@digma.ai
Project-URL: Bug Reports, https://github.com/digma-ai/opentelemetry-instrumentation-digma/issues
Project-URL: Source, https://github.com/digma-ai/opentelemetry-instrumentation-digma/
Classifier: Programming Language :: Python :: 3
Classifier: Intended Audience :: Developers
Classifier: License :: OSI Approved :: MIT License
Classifier: Natural Language :: English
Classifier: Operating System :: OS Independent
Requires-Python: >=3.6
Requires-Dist: opentelemetry-sdk (==1.11.1)
Requires-Dist: opentelemetry-exporter-otlp (==1.11.1)
